changelog.rst
pupy/__init__.py
pupy/__main__.py
pupy/_alias.py
pupy/_alias.pyi
pupy/_jasm.py
pupy/_jasm.pyi
pupy/_template.py
pupy/_template.pyi
pupy/_typing.py
pupy/_version.py
pupy/aio.py
pupy/aio.pyi
pupy/amazon.py
pupy/amazon.pyi
pupy/cheese.py
pupy/cheese.pyi
pupy/cli.py
pupy/cli.pyi
pupy/decorations.py
pupy/decorations.pyi
pupy/fmt.py
pupy/fmt.pyi
pupy/foreign.py
pupy/foreign.pyi
pupy/maths.py
pupy/maths.pyi
pupy/savings_n_loads.py
pupy/savings_n_loads.pyi
pupy/sh.py
pupy/sh.pyi
pupy/sodoku.py
pupy/sodoku.pyi
pupy/ui.py
pupy/ui.pyi
pupy/utils.py
pupy/utils.pyi
pyproject.toml
readme.md
setup.py
pupy-2.23.0.dist-info/entry_points.txt
pupy-2.23.0.dist-info/LICENSE
pupy-2.23.0.dist-info/WHEEL
pupy-2.23.0.dist-info/METADATA
pupy-2.23.0.dist-info/RECORD
