Metadata-Version: 2.1
Name: pupy
Version: 2.23.0
Summary: pretty useful python
Home-page: https://github.com/jessekrubin/pupy
License: BSD-2-Clause
Keywords: useful,utils,tool,cli
Author: jessekrubin
Author-email: jessekrubin@gmail.com
Requires-Python: >=3.5,<4.0
Classifier: Development Status :: 5 - Production/Stable
Classifier: Intended Audience :: Developers
Classifier: License :: OSI Approved :: BSD License
Classifier: Operating System :: Microsoft :: Windows
Classifier: Operating System :: POSIX
Classifier: Operating System :: Unix
Classifier: Programming Language :: Python
Classifier: Programming Language :: Python :: 3
Classifier: Programming Language :: Python :: 3.5
Classifier: Programming Language :: Python :: 3.6
Classifier: Programming Language :: Python :: 3.7
Classifier: Programming Language :: Python :: Implementation :: CPython
Classifier: Programming Language :: Python :: Implementation :: PyPy
Classifier: Topic :: Utilities
Provides-Extra: io
Requires-Dist: aiofiles (>=0.4.0,<0.5.0); extra == "io"
Requires-Dist: msgpack (>=0.6.1,<0.7.0); extra == "io"
Requires-Dist: python-rapidjson (>=0.7.2,<0.8.0); extra == "io"
Requires-Dist: ruamel.yaml (>=0.15.97,<0.16.0); extra == "io"
Requires-Dist: toml (>=0.10.0,<0.11.0); extra == "io"
Project-URL: Repository, https://github.com/jessekrubin/pupy
